bioio_bioformats/__init__.py
bioio_bioformats/biofile.py
bioio_bioformats/coremeta.py
bioio_bioformats/py.typed
bioio_bioformats/reader.py
bioio_bioformats/reader_metadata.py
bioio_bioformats/utils.py
bioio_bioformats-1.3.2.dist-info/licenses/LICENSE
scripts/benchmark.py
bioio_bioformats-1.3.2.dist-info/METADATA
bioio_bioformats-1.3.2.dist-info/WHEEL
bioio_bioformats-1.3.2.dist-info/entry_points.txt
bioio_bioformats-1.3.2.dist-info/top_level.txt
bioio_bioformats-1.3.2.dist-info/RECORD
